ShoubashouJiaoNiShixianJianyiBiteBiJavaBan/README.md
ShoubashouJiaoNiShixianJianyiBiteBiJavaBan/__init__.py
ShoubashouJiaoNiShixianJianyiBiteBiJavaBan/__main__.py
ShoubashouJiaoNiShixianJianyiBiteBiJavaBan/file.epub
ShoubashouJiaoNiShixianJianyiBiteBiJavaBan/index.html
ShoubashouJiaoNiShixianJianyiBiteBiJavaBan/css/__init__.py
ShoubashouJiaoNiShixianJianyiBiteBiJavaBan/css/annotations.css
ShoubashouJiaoNiShixianJianyiBiteBiJavaBan/css/main.css
ShoubashouJiaoNiShixianJianyiBiteBiJavaBan/css/normalize.css
ShoubashouJiaoNiShixianJianyiBiteBiJavaBan/css/popup.css
ShoubashouJiaoNiShixianJianyiBiteBiJavaBan/font/__init__.py
ShoubashouJiaoNiShixianJianyiBiteBiJavaBan/font/fontello.eot
ShoubashouJiaoNiShixianJianyiBiteBiJavaBan/font/fontello.svg
ShoubashouJiaoNiShixianJianyiBiteBiJavaBan/font/fontello.ttf
ShoubashouJiaoNiShixianJianyiBiteBiJavaBan/font/fontello.woff
ShoubashouJiaoNiShixianJianyiBiteBiJavaBan/img/__init__.py
ShoubashouJiaoNiShixianJianyiBiteBiJavaBan/img/annotator-glyph-sprite.png
ShoubashouJiaoNiShixianJianyiBiteBiJavaBan/img/annotator-icon-sprite.png
ShoubashouJiaoNiShixianJianyiBiteBiJavaBan/img/apple-touch-icon.png
ShoubashouJiaoNiShixianJianyiBiteBiJavaBan/img/cancelfullscreen.png
ShoubashouJiaoNiShixianJianyiBiteBiJavaBan/img/close.png
ShoubashouJiaoNiShixianJianyiBiteBiJavaBan/img/fullscreen.png
ShoubashouJiaoNiShixianJianyiBiteBiJavaBan/img/loader.gif
ShoubashouJiaoNiShixianJianyiBiteBiJavaBan/img/menu-icon.png
ShoubashouJiaoNiShixianJianyiBiteBiJavaBan/img/save.png
ShoubashouJiaoNiShixianJianyiBiteBiJavaBan/img/saved.png
ShoubashouJiaoNiShixianJianyiBiteBiJavaBan/img/settings-s.png
ShoubashouJiaoNiShixianJianyiBiteBiJavaBan/img/settings.png
ShoubashouJiaoNiShixianJianyiBiteBiJavaBan/img/star.png
ShoubashouJiaoNiShixianJianyiBiteBiJavaBan/js/__init__.py
ShoubashouJiaoNiShixianJianyiBiteBiJavaBan/js/epub.js
ShoubashouJiaoNiShixianJianyiBiteBiJavaBan/js/epub.min.js
ShoubashouJiaoNiShixianJianyiBiteBiJavaBan/js/epub.min.map
shoubashou_jiao_ni_shixian_jianyi_bite_bi_java_ban-2024.3.5.0.dist-info/METADATA
shoubashou_jiao_ni_shixian_jianyi_bite_bi_java_ban-2024.3.5.0.dist-info/WHEEL
shoubashou_jiao_ni_shixian_jianyi_bite_bi_java_ban-2024.3.5.0.dist-info/entry_points.txt
shoubashou_jiao_ni_shixian_jianyi_bite_bi_java_ban-2024.3.5.0.dist-info/top_level.txt
shoubashou_jiao_ni_shixian_jianyi_bite_bi_java_ban-2024.3.5.0.dist-info/RECORD
